{
  "kind": "Input",
  "meta": {
    "baseURL": null,
    "circularNames": [],
    "enumNames": [],
    "title": "External Ref API",
    "version": "1.0.0"
  },
  "operations": [
    {
      "kind": "Operation",
      "method": "GET",
      "operationId": "listPets",
      "parameters": [],
      "path": "/pets",
      "protocol": "http",
      "responses": [
        {
          "content": [
            {
              "contentType": "application/json",
              "keysToOmit": null,
              "kind": "Content",
              "schema": {
                "kind": "Schema",
                "name": "Pet",
                "ref": "#/components/schemas/Pet",
                "schema": {
                  "kind": "Schema",
                  "primitive": "object",
                  "properties": [
                    {
                      "kind": "Property",
                      "name": "name",
                      "required": true,
                      "schema": {
                        "kind": "Schema",
                        "name": null,
                        "primitive": "string",
                        "type": "string"
                      }
                    },
                    {
                      "kind": "Property",
                      "name": "tag",
                      "required": false,
                      "schema": {
                        "kind": "Schema",
                        "name": null,
                        "optional": true,
                        "primitive": "string",
                        "type": "string"
                      }
                    }
                  ],
                  "type": "object"
                },
                "type": "ref"
              }
            }
          ],
          "description": "A list of pets",
          "kind": "Response",
          "statusCode": "200"
        }
      ],
      "tags": []
    }
  ],
  "schemas": [
    {
      "kind": "Schema",
      "name": "Pet",
      "primitive": "object",
      "properties": [
        {
          "kind": "Property",
          "name": "name",
          "required": true,
          "schema": {
            "kind": "Schema",
            "name": "PetName",
            "primitive": "string",
            "type": "string"
          }
        },
        {
          "kind": "Property",
          "name": "tag",
          "required": false,
          "schema": {
            "kind": "Schema",
            "name": "PetTag",
            "optional": true,
            "primitive": "string",
            "type": "string"
          }
        }
      ],
      "type": "object"
    }
  ]
}